toolmate/README.md
toolmate/config.py
toolmate/main.py
toolmate/package_name.txt
toolmate/requirements.txt
toolmate-2.0.1.dist-info/METADATA
toolmate-2.0.1.dist-info/WHEEL
toolmate-2.0.1.dist-info/entry_points.txt
toolmate-2.0.1.dist-info/top_level.txt
toolmate-2.0.1.dist-info/RECORD
