Metadata-Version: 2.1
Name: toolmate
Version: 2.0.1
Summary: ToolMate AI, developed by Eliran Wong, is a cutting-edge AI companion that seamlessly integrates agents, tools, and plugins to excel in conversations, generative work, and task execution. Supports custom workflow and plugins to automate multi-step actions.
Home-page: https://toolmate.ai
Author: Eliran Wong
Author-email: support@toolmate.ai
License: GNU General Public License (GPL)
Project-URL: Source, https://github.com/eliranwong/toolmate
Project-URL: Tracker, https://github.com/eliranwong/toolmate/issues
Project-URL: Documentation, https://github.com/eliranwong/toolmate/wiki
Project-URL: Funding, https://www.paypal.me/toolmate
Keywords: ai assistant ollama llama llamacpp groq openai chatgpt gemini autogen rag agent stable-diffusion fabric dalle imagen
Classifier: Development Status :: 5 - Production/Stable
Classifier: Intended Audience :: End Users/Desktop
Classifier: Topic :: Utilities
Classifier: Topic :: Scientific/Engineering :: Artificial Intelligence
Classifier: Topic :: Software Development :: Build Tools
Classifier: License :: OSI Approved :: GNU General Public License v3 or later (GPLv3+)
Classifier: Programming Language :: Python :: 3.8
Classifier: Programming Language :: Python :: 3.9
Classifier: Programming Language :: Python :: 3.10
Classifier: Programming Language :: Python :: 3.11
Classifier: Programming Language :: Python :: 3.12
Requires-Python: >=3.8, <3.13
Requires-Dist: agentmake>=1.0.13
Provides-Extra: genai
Requires-Dist: google-genai>=1.1.0; extra == "genai"
